Metadata-Version: 1.1
Name: filesdownloader
Version: 0.0.1
Summary: Fast download mulitple files from web
Home-page: https://github.com/spidezad/filesdownloader
Author: Tan Kok Hua
Author-email: kokhua81@gmail.com
License: BSD
Download-URL: https://github.com/spidezad/filesdownloader/tarball/0.0.1
Platform: UNKNOWN
Classifier: Development Status :: 3 - Alpha
Classifier: Intended Audience :: Developers
Classifier: Programming Language :: Python :: 3
